model/__init__.py
model/binder.py
model/datatypes.py
model/model_base.py
pymvc/__init__.py
pymvc/controller.py
pymvc/pkg_info.py
pymvc/router.py
pymvc/settings.py
pymvc/test.py
pymvc/wsgi.py
pymvc/model/__init__.py
pymvc/model/binder.py
pymvc/model/datatypes.py
pymvc/model/hash_function.py
pymvc/model/model_base.py
pymvc-0.1.3.dist-info/METADATA
pymvc-0.1.3.dist-info/RECORD
pymvc-0.1.3.dist-info/WHEEL
pymvc-0.1.3.dist-info/top_level.txt
src/__init__.py
src/controller.py
src/pkg_info.py
src/router.py
src/settings.py
src/test.py
src/wsgi.py
src/model/__init__.py
src/model/binder.py
src/model/datatypes.py
src/model/model_base.py
