Metadata-Version: 2.1
Name: pymvc
Version: 0.1.3
Summary: MVC framework for Python
Home-page: https://github.com/SiLeader/pymvc
Author: SiLeader and Cerussite
License: Apache 2.0
Platform: UNKNOWN
Classifier: Development Status :: 4 - Beta
Classifier: Framework :: Flask
Classifier: Intended Audience :: Developers
Classifier: Intended Audience :: System Administrators
Classifier: License :: OSI Approved
Classifier: License :: OSI Approved :: Apache Software License
Classifier: Programming Language :: Python
Classifier: Programming Language :: Python :: 3 :: Only
Classifier: Programming Language :: Python :: 3.5
Classifier: Programming Language :: Python :: 3.6
Classifier: Programming Language :: Python :: 3.7
Classifier: Topic :: Internet :: WWW/HTTP :: WSGI :: Middleware
Requires-Dist: click (==6.7)
Requires-Dist: Flask (==1.0.2)
Requires-Dist: itsdangerous (==0.24)
Requires-Dist: Jinja2 (==2.10)
Requires-Dist: MarkupSafe (==1.0)
Requires-Dist: pymongo (==3.7.0)
Requires-Dist: Werkzeug (==0.14.1)
